agfra_s7/__init__.py
agfra_s7/client_s7.py
agS7-1.0.0.2.dist-info/METADATA
agS7-1.0.0.2.dist-info/WHEEL
agS7-1.0.0.2.dist-info/top_level.txt
agS7-1.0.0.2.dist-info/RECORD
