Metadata-Version: 2.1
Name: agS7
Version: 1.0.0.2
Summary: Lectura a DB de un PLC SIEMENS
Home-page: https://agfra.es/
Author: Sdaroca
Author-email: sdaroca@agfra.com
License: MIT
Requires-Dist: python-snap7
